Flask_DStore-0.1.2.dist-info/DESCRIPTION.rst
Flask_DStore-0.1.2.dist-info/METADATA
Flask_DStore-0.1.2.dist-info/RECORD
Flask_DStore-0.1.2.dist-info/WHEEL
Flask_DStore-0.1.2.dist-info/metadata.json
Flask_DStore-0.1.2.dist-info/top_level.txt
flask_dstore/API.py
flask_dstore/JSClient.py
flask_dstore/JSModel.py
flask_dstore/Route.py
flask_dstore/__init__.py
